dmotd/__init__.py
dmotd/__main__.py
dmotd/daemon.py
dmotd-0.0.2.dist-info/LICENSE
dmotd-0.0.2.dist-info/METADATA
dmotd-0.0.2.dist-info/WHEEL
dmotd-0.0.2.dist-info/top_level.txt
dmotd-0.0.2.dist-info/RECORD
