Metadata-Version: 2.1
Name: dmotd
Version: 0.0.2
Summary: Dynamic Message Of The Day.
Home-page: http://github.com/monolix/dmotd
Author: Monolix
Author-email: monolix.team@gmail.com
License: MIT
Platform: UNKNOWN
Requires-Dist: certifi (==2018.11.29)
Requires-Dist: chardet (==3.0.4)
Requires-Dist: Click (==7.0)
Requires-Dist: Flask (==1.0.2)
Requires-Dist: idna (==2.8)
Requires-Dist: itsdangerous (==1.1.0)
Requires-Dist: Jinja2 (==2.10)
Requires-Dist: MarkupSafe (==1.1.0)
Requires-Dist: requests (==2.21.0)
Requires-Dist: urllib3 (==1.24.1)
Requires-Dist: Werkzeug (==0.14.1)
